pyesasky/__init__.py
pyesasky/_version.py
pyesasky/api_interactions.py
pyesasky/constants.py
pyesasky/descriptors.py
pyesasky/exceptions.py
pyesasky/kernel_comm.py
pyesasky/log_utils.py
pyesasky/message_utils.py
pyesasky/models.py
pyesasky/widgets.py
pyesasky/legacy/legacy_api_interactions.py
pyesasky/legacy/legacy_descriptors.py
pyesasky/legacy/legacy_models.py
pyesasky/legacy/legacy_utils.py
pyesasky-2.0.5.data/data/share/jupyter/labextensions/pyesasky/package.json
pyesasky-2.0.5.data/data/share/jupyter/labextensions/pyesasky/static/728.f2415010d3cee1ef2758.js
pyesasky-2.0.5.data/data/share/jupyter/labextensions/pyesasky/static/817.81b23d0c5258c53357b9.js
pyesasky-2.0.5.data/data/share/jupyter/labextensions/pyesasky/static/remoteEntry.913528375e98c9d1d3a2.js
pyesasky-2.0.5.data/data/share/jupyter/labextensions/pyesasky/static/style.js
pyesasky-2.0.5.data/data/share/jupyter/labextensions/pyesasky/static/third-party-licenses.json
pyesasky-2.0.5.data/data/share/jupyter/labextensions/pyesasky/install.json
pyesasky-2.0.5.dist-info/METADATA
pyesasky-2.0.5.dist-info/WHEEL
pyesasky-2.0.5.dist-info/licenses/LICENSE.md
pyesasky-2.0.5.dist-info/RECORD
