Metadata-Version: 2.4
Name: pyesasky
Version: 2.0.5
Summary: ESASky Python wrapper
Project-URL: Homepage, https://github.com/esdc-esac-esa-int/pyesasky
Project-URL: Bug Tracker, https://github.com/esdc-esac-esa-int/pyesasky/issues
Project-URL: Repository, https://github.com/esdc-esac-esa-int/pyesasky.git
Author-email: European Space Agency <esdc_esasky@sciops.esa.int>
License: # European Space Agency Public License – v2.4 – Permissive (Type 3)
License-File: LICENSE.md
Keywords: jupyter,jupyterlab,jupyterlab-extension
Classifier: Framework :: Jupyter
Classifier: Framework :: Jupyter :: JupyterLab
Classifier: Framework :: Jupyter :: JupyterLab :: 4
Classifier: Framework :: Jupyter :: JupyterLab :: Extensions
Classifier: Framework :: Jupyter :: JupyterLab :: Extensions :: Prebuilt
Classifier: License :: Other/Proprietary License
Classifier: Programming Language :: Python
Classifier: Programming Language :: Python :: 3
Classifier: Programming Language :: Python :: 3.8
Classifier: Programming Language :: Python :: 3.9
Classifier: Programming Language :: Python :: 3.10
Classifier: Programming Language :: Python :: 3.11
Classifier: Programming Language :: Python :: 3.12
Requires-Python: >=3.8
Requires-Dist: ipyfilechooser==0.6.0
Requires-Dist: pandas>=2.2.3
